flask_oidc_verifier/__init__.py
flask_oidc_verifier/caches.py
flask_oidc_verifier/decorators.py
flask_oidc_verifier/jwt_parser.py
flask_oidc_verifier/verification.py
tests/__init__.py
tests/conftest.py
tests/mocks.py
tests/test_decorators.py
flask_oidc_verifier-0.0.8.dist-info/LICENSE
flask_oidc_verifier-0.0.8.dist-info/METADATA
flask_oidc_verifier-0.0.8.dist-info/WHEEL
flask_oidc_verifier-0.0.8.dist-info/top_level.txt
flask_oidc_verifier-0.0.8.dist-info/RECORD
