Metadata-Version: 2.1
Name: flask-oidc-verifier
Version: 0.0.8
Summary: Run oidc token verification
Home-page: https://github.com/vishalkuo/flask-oidc-verifier
Author: Vishal Kuo
Author-email: vishalkuo@gmail.com
License: UNKNOWN
Platform: UNKNOWN
Classifier: Programming Language :: Python :: 3
Classifier: License :: OSI Approved :: MIT License
Classifier: Operating System :: OS Independent
Requires-Python: >=3.8
